{
    "constructors": [],
    "externalReferences": [],
    "id": "01p28000007ald8AAA",
    "innerClasses": [],
    "interfaces": [],
    "key": "01p28000007ald8AAA",
    "methods": [
        {
            "annotations": [],
            "location": {
                "column": 26,
                "line": 3
            },
            "modifiers": [
                "static",
                "webService",
                "global"
            ],
            "name": "getCurrUserSSOInfo",
            "parameters": [],
            "references": [],
            "returnType": "String",
            "type": null
        },
        {
            "annotations": [],
            "location": {
                "column": 24,
                "line": 12
            },
            "modifiers": [
                "static",
                "webService",
                "global"
            ],
            "name": "saveCurrUserSSOInfo",
            "parameters": [
                {
                    "name": "agentId",
                    "type": "String"
                },
                {
                    "name": "pwd",
                    "type": "String"
                },
                {
                    "name": "extension",
                    "type": "String"
                }
            ],
            "references": [],
            "returnType": "void",
            "type": null
        }
    ],
    "name": "Apex_UserInfo",
    "namespace": null,
    "parentClass": "",
    "properties": [],
    "tableDeclaration": {
        "annotations": [],
        "location": {
            "column": 14,
            "line": 1
        },
        "modifiers": [
            "global"
        ],
        "name": "Apex_UserInfo",
        "references": [],
        "type": "Apex_UserInfo"
    },
    "variables": [
        {
            "annotations": [],
            "location": {
                "column": 25,
                "line": 4
            },
            "modifiers": [],
            "name": "u",
            "references": [],
            "type": "User"
        },
        {
            "annotations": [],
            "location": {
                "column": 24,
                "line": 6
            },
            "modifiers": [],
            "name": "JSONString",
            "references": [],
            "type": "String"
        },
        {
            "annotations": [],
            "location": {
                "column": 51,
                "line": 12
            },
            "modifiers": [],
            "name": "agentId",
            "references": [],
            "type": "String"
        },
        {
            "annotations": [],
            "location": {
                "column": 67,
                "line": 12
            },
            "modifiers": [],
            "name": "pwd",
            "references": [],
            "type": "String"
        },
        {
            "annotations": [],
            "location": {
                "column": 79,
                "line": 12
            },
            "modifiers": [],
            "name": "extension",
            "references": [],
            "type": "String"
        },
        {
            "annotations": [],
            "location": {
                "column": 13,
                "line": 13
            },
            "modifiers": [],
            "name": "u",
            "references": [],
            "type": "User"
        }
    ]
}